{
  "schemaVersion": 2,
  "phase": "2-workflow-provider-runtime",
  "step": 0,
  "name": "provider-runtime-config",
  "attempt": 1,
  "worker": {
    "type": "subagent"
  },
  "stepStatus": {
    "status": "completed",
    "summary": "typed provider settings, registry, retry/fallback policy 구현",
    "errorMessage": null,
    "blockedReason": null
  },
  "changedFiles": [
    "src/image_translator/config/__init__.py",
    "src/image_translator/config/settings.py",
    "src/image_translator/providers/__init__.py",
    "src/image_translator/providers/registry.py",
    "src/image_translator/providers/retry.py",
    "tests/unit/config/test_settings.py",
    "tests/unit/providers/test_registry.py",
    "tests/unit/providers/test_retry_policy.py"
  ],
  "validation": [
    "uv run pytest -q tests/unit/config/test_settings.py tests/unit/providers/test_registry.py tests/unit/providers/test_retry_policy.py: 17 passed",
    "uv run ruff check .: passed",
    "uv run mypy src: passed",
    "python3 scripts/validate_project.py: passed"
  ],
  "timestamps": {
    "startedAt": "2026-06-23T20:26:13+0900",
    "finishedAt": "2026-06-23T20:36:15+0900",
    "recordedAt": "2026-06-23T20:36:15+0900"
  }
}
